{
  "title": "20211206_013253.jpg",
  "description": "",
  "imageViews": "49",
  "creationTime": {
    "timestamp": "1638774476",
    "formatted": "Dec 6, 2021, 7:07:56 AM UTC"
  },
  "photoTakenTime": {
    "timestamp": "1638772373",
    "formatted": "Dec 6, 2021, 6:32:53 AM UTC"
  },
  "geoData": {
    "latitude": 0.0,
    "longitude": 0.0,
    "altitude": 0.0,
    "latitudeSpan": 0.0,
    "longitudeSpan": 0.0
  },
  "geoDataExif": {
    "latitude": 0.0,
    "longitude": 0.0,
    "altitude": 0.0,
    "latitudeSpan": 0.0,
    "longitudeSpan": 0.0
  },
  "url": "https://photos.google.com/photo/AF1QipODL_90y0qMlRruHtJojJ0vctfJtpV_kpdQkFwg",
  "googlePhotosOrigin": {
    "mobileUpload": {
      "deviceFolder": {
        "localFolderName": "LinkedIn"
      },
      "deviceType": "ANDROID_PHONE"
    }
  }
}