{
  "title": "IMG_20211120_233138007.jpg",
  "description": "",
  "imageViews": "47",
  "creationTime": {
    "timestamp": "1638158286",
    "formatted": "Nov 29, 2021, 3:58:06 AM UTC"
  },
  "photoTakenTime": {
    "timestamp": "1637469098",
    "formatted": "Nov 21, 2021, 4:31:38 AM UTC"
  },
  "geoData": {
    "latitude": 33.782612,
    "longitude": -84.395147,
    "altitude": 241.199,
    "latitudeSpan": 0.0,
    "longitudeSpan": 0.0
  },
  "geoDataExif": {
    "latitude": 33.782612,
    "longitude": -84.395147,
    "altitude": 241.199,
    "latitudeSpan": 0.0,
    "longitudeSpan": 0.0
  },
  "url": "https://photos.google.com/photo/AF1QipPlzUulPO-13t22MuV5FGBIbVnA-Bt1AaucXr5W",
  "googlePhotosOrigin": {
    "mobileUpload": {
      "deviceFolder": {
        "localFolderName": ""
      },
      "deviceType": "ANDROID_PHONE"
    }
  }
}